[{"Code":"AL","Name":"Albania","Permalink":"albania"},{"Code":"DZ","Name":"Algeria","Permalink":"algeria"},{"Code":"AD","Name":"Andorra","Permalink":"andorra"},{"Code":"AO","Name":"Angola","Permalink":"angola"},{"Code":"AI","Name":"Anguilla","Permalink":"anguilla"},{"Code":"AG","Name":"Antigua and Barbuda","Permalink":"antigua-and-barbuda"},{"Code":"AR","Name":"Argentina","Permalink":"argentina"},{"Code":"AW","Name":"Aruba","Permalink":"aruba"},{"Code":"AU","Name":"Australia","Permalink":"australia"},{"Code":"AT","Name":"Austria","Permalink":"austria"},{"Code":"AZ","Name":"Azerbaijan","Permalink":"azerbaijan"},{"Code":"BS","Name":"Bahamas","Permalink":"bahamas"},{"Code":"BH","Name":"Bahrain","Permalink":"bahrain"},{"Code":"BD","Name":"Bangladesh","Permalink":"bangladesh"},{"Code":"BB","Name":"Barbados","Permalink":"barbados"},{"Code":"BE","Name":"Belgium","Permalink":"belgium"},{"Code":"BZ","Name":"Belize","Permalink":"belize"},{"Code":"BJ","Name":"Benin","Permalink":"benin"},{"Code":"BM","Name":"Bermuda","Permalink":"bermuda"},{"Code":"BO","Name":"Bolivia","Permalink":"bolivia"},{"Code":"BW","Name":"Botswana","Permalink":"botswana"},{"Code":"BR","Name":"Brazil","Permalink":"brazil"},{"Code":"VG","Name":"British Virgin Islands","Permalink":"british-virgin-islands"},{"Code":"BN","Name":"Brunei","Permalink":"brunei"},{"Code":"BG","Name":"Bulgaria","Permalink":"bulgaria"},{"Code":"BF","Name":"Burkina Faso","Permalink":"burkina-faso"},{"Code":"BI","Name":"Burundi","Permalink":"burundi"},{"Code":"KH","Name":"Cambodia","Permalink":"cambodia"},{"Code":"CM","Name":"Cameroon","Permalink":"cameroon"},{"Code":"CA","Name":"Canada","Permalink":"canada"},{"Code":"CV","Name":"Cape Verde","Permalink":"cape-verde"},{"Code":"KY","Name":"Cayman Islands","Permalink":"cayman-islands"},{"Code":"TD","Name":"Chad","Permalink":"chad"},{"Code":"CL","Name":"Chile","Permalink":"chile"},{"Code":"CN","Name":"China","Permalink":"china"},{"Code":"CO","Name":"Colombia","Permalink":"colombia"},{"Code":"KM","Name":"Comoros","Permalink":"comoros"},{"Code":"CG","Name":"Republic of the Congo","Permalink":"republic-of-the-congo"},{"Code":"CK","Name":"Cook Islands","Permalink":"cook-islands"},{"Code":"CR","Name":"Costa Rica","Permalink":"costa-rica"},{"Code":"HR","Name":"Croatia","Permalink":"croatia"},{"Code":"CU","Name":"Cuba","Permalink":"cuba"},{"Code":"CY","Name":"Cyprus","Permalink":"cyprus"},{"Code":"CZ","Name":"Czech Republic","Permalink":"czech-republic"},{"Code":"DK","Name":"Denmark","Permalink":"denmark"},{"Code":"DJ","Name":"Djibouti","Permalink":"djibouti"},{"Code":"DM","Name":"Dominica","Permalink":"dominica"},{"Code":"DO","Name":"Dominican Republic","Permalink":"dominican-republic"},{"Code":"EC","Name":"Ecuador","Permalink":"ecuador"},{"Code":"EG","Name":"Egypt","Permalink":"egypt"},{"Code":"SV","Name":"El Salvador","Permalink":"el-salvador"},{"Code":"GQ","Name":"Equatorial Guinea","Permalink":"equatorial-guinea"},{"Code":"EE","Name":"Estonia","Permalink":"estonia"},{"Code":"ET","Name":"Ethiopia","Permalink":"ethiopia"},{"Code":"FJ","Name":"Fiji","Permalink":"fiji"},{"Code":"FI","Name":"Finland","Permalink":"finland"},{"Code":"FR","Name":"France","Permalink":"france"},{"Code":"GF","Name":"French Guiana","Permalink":"french-guiana"},{"Code":"PF","Name":"French Polynesia","Permalink":"french-polynesia"},{"Code":"GA","Name":"Gabon","Permalink":"gabon"},{"Code":"GM","Name":"Gambia","Permalink":"gambia"},{"Code":"DE","Name":"Germany","Permalink":"germany"},{"Code":"GH","Name":"Ghana","Permalink":"ghana"},{"Code":"GI","Name":"Gibraltar","Permalink":"gibraltar"},{"Code":"GR","Name":"Greece","Permalink":"greece"},{"Code":"GD","Name":"Grenada","Permalink":"grenada"},{"Code":"GP","Name":"Guadeloupe","Permalink":"guadeloupe"},{"Code":"GU","Name":"Guam","Permalink":"guam"},{"Code":"GT","Name":"Guatemala","Permalink":"guatemala"},{"Code":"GN","Name":"Guinea","Permalink":"guinea"},{"Code":"GW","Name":"Guinea-Bissau","Permalink":"guinea-bissau"},{"Code":"GY","Name":"Guyana","Permalink":"guyana"},{"Code":"HT","Name":"Haiti","Permalink":"haiti"},{"Code":"HN","Name":"Honduras","Permalink":"honduras"},{"Code":"HK","Name":"Hong Kong","Permalink":"hong-kong"},{"Code":"HU","Name":"Hungary","Permalink":"hungary"},{"Code":"IS","Name":"Iceland","Permalink":"iceland"},{"Code":"IN","Name":"India","Permalink":"india"},{"Code":"ID","Name":"Indonesia","Permalink":"indonesia"},{"Code":"IE","Name":"Ireland","Permalink":"ireland"},{"Code":"IL","Name":"Israel","Permalink":"israel"},{"Code":"IT","Name":"Italy","Permalink":"italy"},{"Code":"CI","Name":"Cote d'Ivoire","Permalink":"cote-divoire"},{"Code":"JM","Name":"Jamaica","Permalink":"jamaica"},{"Code":"JP","Name":"Japan","Permalink":"japan"},{"Code":"JO","Name":"Jordan","Permalink":"jordan"},{"Code":"KZ","Name":"Kazakhstan","Permalink":"kazakhstan"},{"Code":"KE","Name":"Kenya","Permalink":"kenya"},{"Code":"KI","Name":"Kiribati","Permalink":"kiribati"},{"Code":"KR","Name":"South Korea","Permalink":"south-korea"},{"Code":"KW","Name":"Kuwait","Permalink":"kuwait"},{"Code":"LA","Name":"Laos","Permalink":"laos"},{"Code":"LV","Name":"Latvia","Permalink":"latvia"},{"Code":"LB","Name":"Lebanon","Permalink":"lebanon"},{"Code":"LS","Name":"Lesotho","Permalink":"lesotho"},{"Code":"LR","Name":"Liberia","Permalink":"liberia"},{"Code":"LY","Name":"Libya","Permalink":"libya"},{"Code":"LT","Name":"Lithuania","Permalink":"lithuania"},{"Code":"LU","Name":"Luxembourg","Permalink":"luxembourg"},{"Code":"MO","Name":"Macau","Permalink":"macau"},{"Code":"MK","Name":"F.Y.R.O. Macedonia","Permalink":"fyro-macedonia"},{"Code":"MG","Name":"Madagascar","Permalink":"madagascar"},{"Code":"MW","Name":"Malawi","Permalink":"malawi"},{"Code":"MY","Name":"Malaysia","Permalink":"malaysia"},{"Code":"MV","Name":"Maldives","Permalink":"maldives"},{"Code":"ML","Name":"Mali","Permalink":"mali"},{"Code":"MT","Name":"Malta","Permalink":"malta"},{"Code":"MP","Name":"Northern Mariana Islands","Permalink":"northern-mariana-islands"},{"Code":"MQ","Name":"Martinique","Permalink":"martinique"},{"Code":"MR","Name":"Mauritania","Permalink":"mauritania"},{"Code":"MU","Name":"Mauritius","Permalink":"mauritius"},{"Code":"YT","Name":"Mayotte","Permalink":"mayotte"},{"Code":"MX","Name":"Mexico","Permalink":"mexico"},{"Code":"FM","Name":"Federated States of Micronesia","Permalink":"federated-states-of-micronesia"},{"Code":"MC","Name":"Monaco","Permalink":"monaco"},{"Code":"MS","Name":"Montserrat","Permalink":"montserrat"},{"Code":"MA","Name":"Morocco","Permalink":"morocco"},{"Code":"MZ","Name":"Mozambique","Permalink":"mozambique"},{"Code":"MM","Name":"Myanmar","Permalink":"myanmar"},{"Code":"NA","Name":"Namibia","Permalink":"namibia"},{"Code":"NR","Name":"Nauru","Permalink":"nauru"},{"Code":"NP","Name":"Nepal","Permalink":"nepal"},{"Code":"NL","Name":"Netherlands","Permalink":"netherlands"},{"Code":"KN","Name":"St. Kitts and Nevis","Permalink":"st-kitts-and-nevis"},{"Code":"NC","Name":"New Caledonia","Permalink":"new-caledonia"},{"Code":"PG","Name":"Papua New Guinea","Permalink":"papua-new-guinea"},{"Code":"NZ","Name":"New Zealand","Permalink":"new-zealand"},{"Code":"NI","Name":"Nicaragua","Permalink":"nicaragua"},{"Code":"NE","Name":"Niger","Permalink":"niger"},{"Code":"NG","Name":"Nigeria","Permalink":"nigeria"},{"Code":"NF","Name":"Norfolk Island","Permalink":"norfolk-island"},{"Code":"NO","Name":"Norway","Permalink":"norway"},{"Code":"OM","Name":"Oman","Permalink":"oman"},{"Code":"PK","Name":"Pakistan","Permalink":"pakistan"},{"Code":"PW","Name":"Palau","Permalink":"palau"},{"Code":"PA","Name":"Panama","Permalink":"panama"},{"Code":"PY","Name":"Paraguay","Permalink":"paraguay"},{"Code":"PE","Name":"Peru","Permalink":"peru"},{"Code":"PH","Name":"Philippines","Permalink":"philippines"},{"Code":"PL","Name":"Poland","Permalink":"poland"},{"Code":"PT","Name":"Portugal","Permalink":"portugal"},{"Code":"PR","Name":"Puerto Rico","Permalink":"puerto-rico"},{"Code":"QA","Name":"Qatar","Permalink":"qatar"},{"Code":"RE","Name":"Reunion","Permalink":"reunion"},{"Code":"RO","Name":"Romania","Permalink":"romania"},{"Code":"RU","Name":"Russia","Permalink":"russia"},{"Code":"RW","Name":"Rwanda","Permalink":"rwanda"},{"Code":"WS","Name":"Samoa","Permalink":"samoa"},{"Code":"ST","Name":"Sao Tome and Principe","Permalink":"sao-tome-and-principe"},{"Code":"SA","Name":"Saudi Arabia","Permalink":"saudi-arabia"},{"Code":"SN","Name":"Senegal","Permalink":"senegal"},{"Code":"SC","Name":"Seychelles","Permalink":"seychelles"},{"Code":"SL","Name":"Sierra Leone","Permalink":"sierra-leone"},{"Code":"SG","Name":"Singapore","Permalink":"singapore"},{"Code":"SK","Name":"Slovakia","Permalink":"slovakia"},{"Code":"SB","Name":"Solomon Islands","Permalink":"solomon-islands"},{"Code":"ZA","Name":"South Africa","Permalink":"south-africa"},{"Code":"ES","Name":"Spain","Permalink":"spain"},{"Code":"LK","Name":"Sri Lanka","Permalink":"sri-lanka"},{"Code":"LC","Name":"St. Lucia","Permalink":"st-lucia"},{"Code":"VC","Name":"St. Vincent and the Grenadines","Permalink":"st-vincent-and-the-grenadines"},{"Code":"SR","Name":"Suriname","Permalink":"suriname"},{"Code":"SZ","Name":"Swaziland","Permalink":"swaziland"},{"Code":"SE","Name":"Sweden","Permalink":"sweden"},{"Code":"CH","Name":"Switzerland","Permalink":"switzerland"},{"Code":"TW","Name":"Taiwan","Permalink":"taiwan"},{"Code":"TZ","Name":"Tanzania","Permalink":"tanzania"},{"Code":"TH","Name":"Thailand","Permalink":"thailand"},{"Code":"TG","Name":"Togo","Permalink":"togo"},{"Code":"TO","Name":"Tonga","Permalink":"tonga"},{"Code":"TT","Name":"Trinidad and Tobago","Permalink":"trinidad-and-tobago"},{"Code":"TN","Name":"Tunisia","Permalink":"tunisia"},{"Code":"TR","Name":"Turkey","Permalink":"turkey"},{"Code":"TC","Name":"Turks and Caicos","Permalink":"turks-and-caicos"},{"Code":"TV","Name":"Tuvalu","Permalink":"tuvalu"},{"Code":"VI","Name":"U.S. Virgin Islands","Permalink":"us-virgin-islands"},{"Code":"UG","Name":"Uganda","Permalink":"uganda"},{"Code":"UA","Name":"Ukraine","Permalink":"ukraine"},{"Code":"AE","Name":"United Arab Emirates","Permalink":"united-arab-emirates"},{"Code":"GB","Name":"United Kingdom","Permalink":"united-kingdom"},{"Code":"UY","Name":"Uruguay","Permalink":"uruguay"},{"Code":"VU","Name":"Vanuatu","Permalink":"vanuatu"},{"Code":"VE","Name":"Venezuela","Permalink":"venezuela"},{"Code":"VN","Name":"Vietnam","Permalink":"vietnam"},{"Code":"RS","Name":"Serbia","Permalink":"serbia"},{"Code":"CD","Name":"Democratic Republic of the Congo","Permalink":"democratic-republic-of-the-congo"},{"Code":"ZM","Name":"Zambia","Permalink":"zambia"},{"Code":"ZW","Name":"Zimbabwe","Permalink":"zimbabwe"},{"Code":"US","Name":"United States of America","Permalink":"united-states-of-america"},{"Code":"GL","Name":"Greenland","Permalink":"greenland"},{"Code":"AM","Name":"Armenia","Permalink":"armenia"},{"Code":"AS","Name":"American Samoa","Permalink":"american-samoa"},{"Code":"BT","Name":"Bhutan","Permalink":"bhutan"},{"Code":"BY","Name":"Belarus","Permalink":"belarus"},{"Code":"ER","Name":"Eritrea","Permalink":"eritrea"},{"Code":"GE","Name":"Georgia","Permalink":"georgia"},{"Code":"KG","Name":"Kyrgyzstan","Permalink":"kyrgyzstan"},{"Code":"LI","Name":"Liechtenstein","Permalink":"liechtenstein"},{"Code":"MD","Name":"Moldova","Permalink":"moldova"},{"Code":"MH","Name":"Marshall Islands","Permalink":"marshall-islands"},{"Code":"MN","Name":"Mongolia","Permalink":"mongolia"},{"Code":"NU","Name":"Niue","Permalink":"niue"},{"Code":"TJ","Name":"Tajikistan","Permalink":"tajikistan"},{"Code":"TM","Name":"Turkmenistan","Permalink":"turkmenistan"},{"Code":"UZ","Name":"Uzbekistan","Permalink":"uzbekistan"},{"Code":"SI","Name":"Slovenia","Permalink":"slovenia"},{"Code":"BA","Name":"Bosnia and Herzegovina","Permalink":"bosnia-and-herzegovina"},{"Code":"BV","Name":"Bouvet Island","Permalink":"bouvet-island"},{"Code":"IO","Name":"British Indian Ocean Territory","Permalink":"british-indian-ocean-territory"},{"Code":"CX","Name":"Christmas Island","Permalink":"christmas-island"},{"Code":"CC","Name":"Cocos Islands","Permalink":"cocos-islands"},{"Code":"FK","Name":"Falkland Islands","Permalink":"falkland-islands"},{"Code":"TF","Name":"French Southern and Antarctic Territories","Permalink":"french-southern-and-antarctic-territories"},{"Code":"HM","Name":"Heard and McDonald Islands","Permalink":"heard-and-mcdonald-islands"},{"Code":"FO","Name":"Faroe Islands","Permalink":"faroe-islands"},{"Code":"PN","Name":"Pitcairn Island","Permalink":"pitcairn-island"},{"Code":"PM","Name":"St. Pierre and Miquelon","Permalink":"st-pierre-and-miquelon"},{"Code":"SM","Name":"San Marino","Permalink":"san-marino"},{"Code":"SH","Name":"St. Helena","Permalink":"st-helena"},{"Code":"SJ","Name":"Svalbard","Permalink":"svalbard"},{"Code":"TK","Name":"Tokelau","Permalink":"tokelau"},{"Code":"VA","Name":"Vatican City","Permalink":"vatican-city"},{"Code":"WF","Name":"Wallis and Futuna","Permalink":"wallis-and-futuna"},{"Code":"PS","Name":"State of Palestine","Permalink":"state-of-palestine"},{"Code":"ME","Name":"Montenegro","Permalink":"montenegro"},{"Code":"BL","Name":"St. Barthelemy","Permalink":"st-barthelemy"},{"Code":"MF","Name":"St. Martin","Permalink":"st-martin"},{"Code":"BQ","Name":"Bonaire, Sint Eustatius and Saba","Permalink":"bonaire,-sint-eustatius-and-saba"},{"Code":"CW","Name":"Curacao","Permalink":"curacao"},{"Code":"SX","Name":"Sint Maarten","Permalink":"sint-maarten"},{"Code":"UM","Name":"US Minor Outlying Islands","Permalink":"us-minor-outlying-islands"}]